apgp/__init__.py
apgp/config.py
apgp/core.py
apgp/db.py
apgp/exceptions.py
apgp-0.1.dist-info/DESCRIPTION.rst
apgp-0.1.dist-info/METADATA
apgp-0.1.dist-info/RECORD
apgp-0.1.dist-info/WHEEL
apgp-0.1.dist-info/metadata.json
apgp-0.1.dist-info/top_level.txt
