Metadata-Version: 2.0
Name: apgp
Version: 0.1
Summary: Asynchronous Postgres to Pandas
Home-page: https://github.com/beigebrucewayne/apgp
Author: kade killary
Author-email: kadekillary@protonmail.com
License: MIT
Platform: UNKNOWN
Classifier: License :: OSI Approved :: MIT License
Classifier: Programming Language :: Python
Classifier: Programming Language :: Python :: 3
Classifier: Programming Language :: Python :: 3.6
Classifier: Programming Language :: Python :: Implementation :: CPython
Classifier: Programming Language :: Python :: Implementation :: PyPy
Requires-Python: >=3.6.0
Requires-Dist: pandas
Requires-Dist: asyncpg
Requires-Dist: pyyaml
